{"kirarothekitsune":"User's appearence: http://prntscr.com/e9aodn","karenchanx":"User's appearence: http://prntscr.com/e98auq","roomsong":"[[Ellie Goulding - Love Me Like You Do]]","letaldos":"User's Appearence: http://prntscr.com/eayh2z","thekarenchansong":"Dese desu desu! https://m.youtube.com/watch?v=60mLvBWOMb4","divideby0":"/leave","natsuyuuki":"User's Appearence: http://prnt.sc/edljro","kiraroxliquor":"https://m.youtube.com/watch?v=O63LMcuzens","kirarospower":"https://m.youtube.com/watch?v=FLz8lJP0p2g","kiraroscourage":"https://m.youtube.com/watch?v=YcscgwwlY7g","dancingkiraro":"https://m.youtube.com/watch?v=H6vkCeY98Aw","kiraroswedding":"https://www.youtube.com/watch?v=wL0j6N1BkhI"}